r3xa/__init__.py
r3xa/gui.py
r3xa/metadata.py
r3xa/scripts.py
r3xa/utils.py
r3xa/validation.py
r3xa/visualisation.py
resources/schema.json
r3xa-2024.7.1.dist-info/METADATA
r3xa-2024.7.1.dist-info/WHEEL
r3xa-2024.7.1.dist-info/entry_points.txt
r3xa-2024.7.1.dist-info/RECORD
