Metadata-Version: 2.1
Name: r3xa
Version: 2024.7.1
Summary: Remember, Reuse and Replicate eXperiments and Analyses
Home-page: https://photomecanics.gitlab.io/r3xa/doc
Author: Emmanuel Roubin
Author-email: emmanuel.roubin@univ-grenoble-alpes.fr
Maintainer: Emmanuel Roubin
Maintainer-email: emmanuel.roubin@univ-grenoble-alpes.fr
Requires-Python: >=3.9,<3.13
Classifier: License :: Public Domain
Classifier: Natural Language :: French
Classifier: Programming Language :: Python :: 3
Classifier: Programming Language :: Python :: 3.9
Classifier: Programming Language :: Python :: 3.10
Classifier: Programming Language :: Python :: 3.11
Classifier: Programming Language :: Python :: 3.12
Requires-Dist: PyQt5 (==5.15.2) ; sys_platform == "linux"
Requires-Dist: PyQt5 ; sys_platform == "win32" or sys_platform == "darwin"
Requires-Dist: Pygments (==2.17.2)
Requires-Dist: jsonschema (==4.21.1)
Requires-Dist: python-slugify (==8.0.4)
Requires-Dist: pyvis (==0.3.2)
Project-URL: Repository, https://gitlab.com/photomecanics/r3xa
